ddipy/__init__.py
ddipy/_version.py
ddipy/cli.py
ddipy/commons.py
ddipy/constants.py
ddipy/database_client.py
ddipy/dataset_client.py
ddipy/dblucenemapping_client.py
ddipy/ddi_utils.py
ddipy/enrichement_client.py
ddipy/feedback_client.py
ddipy/publication_client.py
ddipy/seo_client.py
ddipy/statistics_client.py
ddipy/term_client.py
tests/__init__.py
tests/test_database_client.py
tests/test_dataset.py
tests/test_dataset_client.py
tests/test_seo_client.py
tests/test_statistics_client.py
tests/test_term_client.py
ddipy-0.0.5.dist-info/LICENSE
ddipy-0.0.5.dist-info/METADATA
ddipy-0.0.5.dist-info/WHEEL
ddipy-0.0.5.dist-info/entry_points.txt
ddipy-0.0.5.dist-info/top_level.txt
ddipy-0.0.5.dist-info/RECORD
