Metadata-Version: 2.1
Name: ddipy
Version: 0.0.5
Summary: Python client for OmicsDI Restful API
Home-page: https://github.com/OmicsDI/ddipy
Author: OmicsDI Team
Author-email: ypriverol@gmail.com
License: LICENSE
Keywords: pip,omicsDI,WS-client
Platform: any
Requires-Python: >=3.4
Requires-Dist: requests (==2.22.0)
Requires-Dist: pytest
Requires-Dist: click
Requires-Dist: pyOpenSSL
